music_anim_utils/__init__.py
music_anim_utils-0.0.1.dist-info/LICENSE
music_anim_utils-0.0.1.dist-info/METADATA
music_anim_utils-0.0.1.dist-info/WHEEL
music_anim_utils-0.0.1.dist-info/top_level.txt
music_anim_utils-0.0.1.dist-info/RECORD
